<?xml version="1.0" encoding="utf-8"?>

<NPCCharacters> 

  <!--Hungarian Lords-->  

  <NPCCharacter id="lord_hungary_1a"
    name="{=lord_hungary_1a.name}Coloman the Learned"
    voice="softspoken"
    age="26"
    is_female="false"
    is_hero="true"
    culture="Culture.hungary"
    occupation="Lord"
    default_group="Cavalry">
    <face>
      <!-- Face key needs redoing, repurposed from female-->
      <BodyProperties version="4" age="22.21" weight="0.3901" build="0.7495"  key="00059006C070391B2673D992875A457D7C463A41DCD78896B58518AC3B446A77009B66030989886A000000000000000000000000000000000000000049346002"  />
    </face>
    <skills>
      <skill id="Engineering" value="150" />
      <skill id="Medicine" value="125" />
      <skill id="Leadership" value="125" />
      <skill id="Steward" value="175" />
      <skill id="Trade" value="100" />
      <skill id="Charm" value="100" />
      <skill id="Roguery" value="125" />
      <skill id="Scouting" value="75" />
      <skill id="Tactics" value="175" />
      <skill id="Crafting" value="75" />
      <skill id="Athletics" value="100" />
      <skill id="Riding" value="175" />
      <skill id="Throwing" value="50" />
      <skill id="Crossbow" value="100" />
      <skill id="Bow" value="50" />
      <skill id="Polearm" value="200" />
      <skill id="TwoHanded" value="50" />
      <skill id="OneHanded" value="150" />
    </skills>
    <Traits>
      <Trait id="Mercy" value="0" />
      <Trait id="Valor" value="0" />
      <Trait id="Honor" value="1" />
      <Trait id="Generosity" value="0" />
      <Trait id="Calculating" value="1" />
      <Trait id="Egalitarian" value="0" />
      <Trait id="Oligarchic" value="1" />
      <Trait id="Authoritarian" value="-1" />
    </Traits>
    <Equipments>
      <EquipmentSet id="hun_king" />
      <EquipmentSet id="hun_king"
                    civilian="true" />
    </Equipments>
  </NPCCharacter>
  
  <NPCCharacter id="lord_hungary_1b"
    name="{=lord_hungary_1b.name}Felicia Hauteville of Sicily"
    default_group="Cavalry"
    age="22"
    voice="ironic"
    is_female="true"
    is_hero="true"
    culture="Culture.sicilian"
    occupation="Lord"
    face_mesh_cache="true">
    <face>
      <BodyProperties version="4" age="22.21" weight="0.3901" build="0.7495"  key="00059006C07010062673D992875A457D7C463A41DCD78896B58518AC3B446A77009B66030989886A0000000000000000000000000000000000000000493440C3"  />
    </face>
    <skills>
      <skill id="Tactics" value="30" />
      <skill id="Engineering" value="60" />
      <skill id="Medicine" value="100" />
      <skill id="Leadership" value="125" />
      <skill id="Steward" value="150" />
      <skill id="Trade" value="100" />
      <skill id="Charm" value="200" />
      <skill id="Roguery" value="175" />
      <skill id="Scouting" value="150" />
      <skill id="Bow" value="75" />
      <skill id="Crossbow" value="75" />
      <skill id="OneHanded" value="50" />
      <skill id="Riding" value="75" />
      <skill id="Athletics" value="50" />
    </skills>
    <Traits>
      <Trait id="Mercy" value="0" />
      <Trait id="Valor" value="-1" />
      <Trait id="Honor" value="-1" />
      <Trait id="Generosity" value="0" />
      <Trait id="Calculating" value="0" />
      <Trait id="Egalitarian" value="1" />
      <Trait id="Oligarchic" value="-2" />
      <Trait id="Authoritarian" value="1" />
    </Traits>
    <Equipments>
      <EquipmentSet id="hun_queen" />
      <EquipmentSet id="hun_queen"
                    civilian="true" />
    </Equipments>
  </NPCCharacter> 
  
  <NPCCharacter id="lord_hungary_1c"
    name="{=lord_hungary_1c.name}István II of Hungary"
    voice="softspoken"
    age="1"
    is_female="false"
    is_hero="true"
    culture="Culture.hungary"
    occupation="Lord"
    default_group="Cavalry">
    <face>
      <!-- Face key needs redoing, repurposed from female-->
      <BodyProperties version="4" age="22.21" weight="0.149" build="0.7495"  key="0005A80200000A5B72C855567181B978768DD796B9835544755D437CB746B2DA009B260309A9D57200000000000000000000000000000000000000002F2C4102"  />
    </face>
    <skills>
      <skill id="Leadership" value="10" />
      <skill id="Scouting" value="10" />
      <skill id="Athletics" value="5" />
      <skill id="Throwing" value="10" />
    </skills>
    <Traits>
      <Trait id="Mercy" value="2" />
      <Trait id="Valor" value="2" />
      <Trait id="Honor" value="-1" />
      <Trait id="Generosity" value="0" />
      <Trait id="Calculating" value="0" />
      <Trait id="Egalitarian" value="1" />
      <Trait id="Oligarchic" value="-2" />
      <Trait id="Authoritarian" value="0" />
    </Traits>
    <Equipments>
      <EquipmentSet id="hun_lord" />
      <EquipmentSet id="hun_lord"
                    civilian="true" />
    </Equipments>
  </NPCCharacter>
  
   <NPCCharacter id="lord_hungary_1d"
      name="{=lord_hungary_1d.name}Álmos"
      voice="softspoken"
      age="25"
      is_female="false"
      is_hero="true"
      culture="Culture.hungary"
      occupation="Lord"
      default_group="Cavalry">
    <face>
      <!-- Face key needs redoing, repurposed from female-->
      <BodyProperties version="4" age="22.21" weight="0.5355" build="0.4754"  key="0005A80E40B4014D489CA8DB758355859281A399D6B3A54BA9D2A7788A499CDE0047860304884E92000000000000000000000000000000000000000006849142"  />
    </face>
	  <skills>
      <skill id="Engineering" value="100" />
      <skill id="Medicine" value="50" />
      <skill id="Leadership" value="125" />
      <skill id="Steward" value="175" />
      <skill id="Trade" value="50" />
      <skill id="Charm" value="175" />
      <skill id="Roguery" value="200" />
      <skill id="Scouting" value="225" />
      <skill id="Tactics" value="150" />
      <skill id="Athletics" value="100" />
      <skill id="Riding" value="150" />
      <skill id="Throwing" value="50" />
      <skill id="Bow" value="75" />
      <skill id="Crossbow" value="125" />
      <skill id="Polearm" value="225" />
      <skill id="TwoHanded" value="100" />
      <skill id="OneHanded" value="150" />
    </skills>
    <Traits>
      <Trait id="Mercy" value="-1" />
      <Trait id="Valor" value="-2" />
      <Trait id="Honor" value="-2" />
      <Trait id="Generosity" value="-1" />
      <Trait id="Calculating" value="-1" />
      <Trait id="Egalitarian" value="-2" />
      <Trait id="Oligarchic" value="1" />
      <Trait id="Authoritarian" value="-2" />
    </Traits>
    <Equipments>
      <EquipmentSet id="hun_lord" />
      <EquipmentSet id="hun_lord"
                    civilian="true" />
    </Equipments>
  </NPCCharacter>
  
  <NPCCharacter id="lord_hungary_1e"
      name="{=lord_hungary_1e.name}Zsófia"
      default_group="Cavalry"
      age="1"
      voice="ironic"
      is_female="true"
      is_hero="true"
      culture="Culture.sturgia"
      occupation="Lord"
      face_mesh_cache="true">
    <face>
      <BodyProperties version="4" age="22.23" weight="0.3333" build="0.341"  key="0005A40AC07030022685B9928759557B79463A41DCD58886B58518AC39446A77009556030989886A0000000000000000000000000000000000000000493C4003"  />
    </face>
    <skills>
      <skill id="Charm" value="15" />
      <skill id="Roguery" value="10" />
	  </skills>
    <Traits>
      <Trait id="Mercy" value="0" />
      <Trait id="Valor" value="-2" />
      <Trait id="Honor" value="1" />
      <Trait id="Generosity" value="0" />
      <Trait id="Calculating" value="1" />
      <Trait id="Egalitarian" value="0" />
      <Trait id="Oligarchic" value="2" />
      <Trait id="Authoritarian" value="-2" />
    </Traits>
    <Equipments>
      <EquipmentSet id="hun_lady" />
      <EquipmentSet id="hun_lady"
                    civilian="true" />
    </Equipments>
  </NPCCharacter>

  <NPCCharacter id="lord_hungary_1f"
    name="{=lord_hungary_1f.name}Géza I of Hungary"
    voice="softspoken"
    age="33"
    is_female="false"
    is_hero="true"
    culture="Culture.hungary"
    occupation="Lord"
    default_group="Cavalry">
    <face>
      <!-- Face key needs redoing, repurposed from female-->
      <BodyProperties version="4" age="22.23" weight="0.5417" build="0.5262"  key="0005A40AC07033432685B9928759557B79463A41DCD58886B58518AC39446A77008886030889886A000000000000000000000000000000000000000049046002"  />
    </face>
    <skills>
      <skill id="Engineering" value="100" />
      <skill id="Medicine" value="75" />
      <skill id="Leadership" value="225" />
      <skill id="Steward" value="200" />
      <skill id="Trade" value="150" />
      <skill id="Charm" value="175" />
      <skill id="Roguery" value="75" />
      <skill id="Scouting" value="125" />
      <skill id="Tactics" value="200" />
      <skill id="Crafting" value="125" />
      <skill id="Athletics" value="100" />
      <skill id="Riding" value="225" />
      <skill id="Throwing" value="100" />
      <skill id="Crossbow" value="150" />
      <skill id="Bow" value="100" />
      <skill id="Polearm" value="225" />
      <skill id="TwoHanded" value="125" />
      <skill id="OneHanded" value="200" />
    </skills>
    <Traits>
      <Trait id="Mercy" value="0" />
      <Trait id="Valor" value="0" />
      <Trait id="Honor" value="0" />
      <Trait id="Generosity" value="0" />
      <Trait id="Calculating" value="0" />
      <Trait id="Egalitarian" value="0" />
      <Trait id="Oligarchic" value="0" />
      <Trait id="Authoritarian" value="0" />
    </Traits>
    <Equipments>
      <EquipmentSet id="hun_lord" />
      <EquipmentSet id="hun_lord"
                    civilian="true" />
    </Equipments>
  </NPCCharacter>
  
  <NPCCharacter id="lord_hungary_2a"
    name="{=lord_hungary_2a.name}Petar"
    voice="softspoken"
    age="43"
    is_female="false"
    is_hero="true"
    culture="Culture.hungary"
    occupation="Lord"
    default_group="Cavalry">
    <face>
      <!-- Face key needs redoing, repurposed from female-->
      <BodyProperties version="4" age="22.21" weight="0.2601" build="0.4754"  key="00087C040058034A9818A66138B3574988B3ACA9D25779ABA98889518783541900974603099BA49C00000000000000000000000000000000000000004F2C8102"  />
    </face>
	  <skills>
      <skill id="Engineering" value="125" />
      <skill id="Medicine" value="100" />
      <skill id="Leadership" value="250" />
      <skill id="Steward" value="175" />
      <skill id="Trade" value="50" />
      <skill id="Charm" value="150" />
      <skill id="Roguery" value="200" />
      <skill id="Scouting" value="125" />
      <skill id="Tactics" value="175" />
      <skill id="Crafting" value="50" />
      <skill id="Athletics" value="100" />
      <skill id="Riding" value="200" />
      <skill id="Throwing" value="50" />
      <skill id="Crossbow" value="75" />
      <skill id="Bow" value="75" />
      <skill id="Polearm" value="175" />
      <skill id="TwoHanded" value="100" />
      <skill id="OneHanded" value="150" />
    </skills>
    <Traits>
      <Trait id="Mercy" value="1" />
      <Trait id="Valor" value="0" />
      <Trait id="Honor" value="0" />
      <Trait id="Generosity" value="-2" />
      <Trait id="Calculating" value="-2" />
      <Trait id="Egalitarian" value="0" />
      <Trait id="Oligarchic" value="-2" />
      <Trait id="Authoritarian" value="-2" />
    </Traits>
    <Equipments>
      <EquipmentSet id="hun_king" />
      <EquipmentSet id="hun_king"
                    civilian="true" />
    </Equipments>
  </NPCCharacter>

  <NPCCharacter id="lord_hungary_2b"
    name="{=lord_hungary_2b.name}Stjepan*"
    voice="softspoken"
    age="38"
    is_female="false"
    is_hero="true"
    culture="Culture.hungary"
    occupation="Lord"
    default_group="Cavalry">
    <face>
      <!-- Face key needs redoing, repurposed from female-->
      <BodyProperties version="4" age="22.24" weight="0.3951" build="0.6111"  key="000814099758014EA818A6613893574A8893ACA9B25779ABA9888951B783541900996603099BA49A00000000000000000000000000000000000000004F2C6102"  />
    </face>
	  <skills>
      <skill id="Engineering" value="100" />
      <skill id="Medicine" value="75" />
      <skill id="Leadership" value="100" />
      <skill id="Steward" value="125" />
      <skill id="Trade" value="50" />
      <skill id="Charm" value="100" />
      <skill id="Roguery" value="75" />
      <skill id="Scouting" value="100" />
      <skill id="Tactics" value="175" />
      <skill id="Athletics" value="100" />
      <skill id="Riding" value="200" />
      <skill id="Throwing" value="50" />
      <skill id="Crossbow" value="75" />
      <skill id="Bow" value="75" />
      <skill id="Polearm" value="150" />
      <skill id="TwoHanded" value="50" />
      <skill id="OneHanded" value="125" />
    </skills>
    <Traits>
      <Trait id="Mercy" value="-1" />
      <Trait id="Valor" value="2" />
      <Trait id="Honor" value="-1" />
      <Trait id="Generosity" value="0" />
      <Trait id="Calculating" value="0" />
      <Trait id="Egalitarian" value="0" />
      <Trait id="Oligarchic" value="0" />
      <Trait id="Authoritarian" value="0" />
    </Traits>
    <Equipments>
      <EquipmentSet id="hun_lord" />
      <EquipmentSet id="hun_lord"
                    civilian="true" />
    </Equipments>
  </NPCCharacter>

  <NPCCharacter id="lord_hungary_2с"
    name="{=lord_hungary_2с.name}Juraj"
    voice="softspoken"
    age="35"
    is_female="false"
    is_hero="true"
    culture="Culture.hungary"
    occupation="Lord"
    default_group="Cavalry">
    <face>
      <!-- Face key needs redoing, repurposed from female-->
      <BodyProperties version="4" age="22.24" weight="0.5571" build="0.5764"  key="00087C06C05806069818A66138B357498893ACA9D257798BA6888C5167835419006986030679949C00000000000000000000000000000000000000004ED45102"  />
    </face>
	  <skills>
      <skill id="Engineering" value="100" />
      <skill id="Medicine" value="50" />
      <skill id="Leadership" value="200" />
      <skill id="Steward" value="150" />
      <skill id="Trade" value="100" />
      <skill id="Charm" value="175" />
      <skill id="Roguery" value="50" />
      <skill id="Scouting" value="125" />
      <skill id="Tactics" value="150" />
      <skill id="Athletics" value="100" />
      <skill id="Riding" value="175" />
      <skill id="Throwing" value="75" />
      <skill id="Crossbow" value="100" />
      <skill id="Bow" value="50" />
      <skill id="Polearm" value="225" />
      <skill id="TwoHanded" value="75" />
      <skill id="OneHanded" value="125" />
    </skills>
    <Traits>
      <Trait id="Mercy" value="1" />
      <Trait id="Valor" value="0" />
      <Trait id="Honor" value="0" />
      <Trait id="Generosity" value="0" />
      <Trait id="Calculating" value="0" />
      <Trait id="Egalitarian" value="0" />
      <Trait id="Oligarchic" value="2" />
      <Trait id="Authoritarian" value="0" />
    </Traits>
    <Equipments>
      <EquipmentSet id="hun_lord" />
      <EquipmentSet id="hun_lord"
                    civilian="true" />
    </Equipments>
  </NPCCharacter>
  
  <NPCCharacter id="lord_hungary_3a"
    name="{=lord_hungary_3a.name}Bogyoszló"
    voice="softspoken"
    age="51"
    is_female="false"
    is_hero="true"
    culture="Culture.hungary"
    occupation="Lord"
    default_group="Cavalry">
    <face>
      <!-- Face key needs redoing, repurposed from female-->
      <BodyProperties version="4" age="22.13" weight="0.5525" build="0.2986"  key="001BA40C402C1905276854BAA29C387587387874B59C99B9D79A9878B51965BB0054860305A58995000000000000000000000000000000000000000028A42042"  />
    </face>
	  <skills>
      <skill id="Engineering" value="125" />
      <skill id="Medicine" value="100" />
      <skill id="Leadership" value="225" />
      <skill id="Steward" value="225" />
      <skill id="Trade" value="50" />
      <skill id="Charm" value="125" />
      <skill id="Roguery" value="125" />
      <skill id="Scouting" value="75" />
      <skill id="Tactics" value="100" />
      <skill id="Crafting" value="25" />
      <skill id="Athletics" value="100" />
      <skill id="Riding" value="200" />
      <skill id="Throwing" value="35" />
      <skill id="Crossbow" value="50" />
      <skill id="Bow" value="50" />
      <skill id="Polearm" value="225" />
      <skill id="TwoHanded" value="75" />
      <skill id="OneHanded" value="150" />
    </skills>
    <Traits>
      <Trait id="Mercy" value="0" />
      <Trait id="Valor" value="-1" />
      <Trait id="Honor" value="0" />
      <Trait id="Generosity" value="0" />
      <Trait id="Calculating" value="1" />
      <Trait id="Egalitarian" value="0" />
      <Trait id="Oligarchic" value="2" />
      <Trait id="Authoritarian" value="2" />
    </Traits>
    <Equipments>
      <EquipmentSet id="hun_lord" />
      <EquipmentSet id="hun_lord"
                    civilian="true" />
    </Equipments>
  </NPCCharacter>
  
  <NPCCharacter id="lord_hungary_3b"
    name="{=lord_hungary_3b.name}Antonija*"
    default_group="Cavalry"
    age="49"
    voice="ironic"
    is_female="true"
    is_hero="true"
    culture="Culture.hungary"
    occupation="Lord"
    face_mesh_cache="true">
    <face>
      <BodyProperties version="4" age="22.13" weight="0.2562" build="0.2369"  key="001EA40A400000049B95E8B7376596B6DB7C76545D864C64866AA674761589A5006446030659C69600000000000000000000000000000000000000006AC43003"  />
    </face>
    <skills>
      <skill id="Engineering" value="100" />
      <skill id="Medicine" value="50" />
      <skill id="Leadership" value="150" />
      <skill id="Steward" value="275" />
      <skill id="Trade" value="175" />
      <skill id="Charm" value="200" />
      <skill id="Roguery" value="175" />
      <skill id="Scouting" value="100" />
      <skill id="Athletics" value="100" />
      <skill id="Riding" value="125" />
      <skill id="OneHanded" value="50" />
      <skill id="Crossbow" value="75" />
      <skill id="Bow" value="50" />
	  </skills>
    <Traits>
      <Trait id="Mercy" value="-1" />
      <Trait id="Valor" value="-2" />
      <Trait id="Honor" value="-2" />
      <Trait id="Generosity" value="0" />
      <Trait id="Calculating" value="0" />
      <Trait id="Egalitarian" value="0" />
      <Trait id="Oligarchic" value="0" />
      <Trait id="Authoritarian" value="1" />
    </Traits>
    <Equipments>
      <EquipmentSet id="hun_lady" />
      <EquipmentSet id="hun_lady"
                    civilian="true" />
    </Equipments>
  </NPCCharacter> 

  <NPCCharacter id="lord_hungary_3c"
    name="{=lord_hungary_3c.name}Fülöp the Great"
    voice="softspoken"
    age="48"
    is_female="false"
    is_hero="true"
    culture="Culture.hungary"
    occupation="Lord"
    default_group="Cavalry">
    <face>
      <!-- Face key needs redoing, repurposed from female-->
      <BodyProperties version="4" age="22.13" weight="0.7307" build="0.4028"  key="001BC40ACF2C1382266854AAA29A387587367574B59C99B9D79A9E78B51965970076B60307A58995000000000000000000000000000000000000000028DC4042"  />
    </face>
	  <skills>
      <skill id="Engineering" value="100" />
      <skill id="Medicine" value="100" />
      <skill id="Leadership" value="200" />
      <skill id="Steward" value="125" />
      <skill id="Trade" value="50" />
      <skill id="Charm" value="100" />
      <skill id="Roguery" value="100" />
      <skill id="Scouting" value="150" />
      <skill id="Tactics" value="150" />
      <skill id="Athletics" value="100" />
      <skill id="Riding" value="175" />
      <skill id="Throwing" value="50" />
      <skill id="Crossbow" value="50" />
      <skill id="Bow" value="75" />
      <skill id="Polearm" value="175" />
      <skill id="TwoHanded" value="100" />
      <skill id="OneHanded" value="125" />
    </skills>
    <Traits>
      <Trait id="Mercy" value="0" />
      <Trait id="Valor" value="2" />
      <Trait id="Honor" value="1" />
      <Trait id="Generosity" value="1" />
      <Trait id="Calculating" value="0" />
      <Trait id="Egalitarian" value="0" />
      <Trait id="Oligarchic" value="0" />
      <Trait id="Authoritarian" value="0" />
    </Traits>
    <Equipments>
      <EquipmentSet id="hun_lord" />
      <EquipmentSet id="hun_lord"
                    civilian="true" />
    </Equipments>
  </NPCCharacter>

  <NPCCharacter id="lord_hungary_3d"
    name="{=lord_hungary_3d.name}Lőrinc*"
    voice="softspoken"
    age="46"
    is_female="false"
    is_hero="true"
    culture="Culture.hungary"
    occupation="Lord"
    default_group="Cavalry">
    <face>
      <!-- Face key needs redoing, repurposed from female-->
      <BodyProperties version="4" age="22.13" weight="0.5525" build="0.2986"  key="001BDC0D802C13842768549AA299387787387774356579B9A79A9076751965570054860305658995000000000000000000000000000000000000000028A46042"  />
    </face>
	  <skills>
      <skill id="Engineering" value="125" />
      <skill id="Medicine" value="75" />
      <skill id="Leadership" value="175" />
      <skill id="Steward" value="150" />
      <skill id="Trade" value="100" />
      <skill id="Charm" value="125" />
      <skill id="Roguery" value="75" />
      <skill id="Scouting" value="75" />
      <skill id="Tactics" value="100" />
      <skill id="Athletics" value="75" />
      <skill id="Riding" value="150" />
      <skill id="Throwing" value="25" />
      <skill id="Crossbow" value="0" />
      <skill id="Bow" value="100" />
      <skill id="Polearm" value="175" />
      <skill id="TwoHanded" value="50" />
      <skill id="OneHanded" value="75" />
    </skills>
    <Traits>
      <Trait id="Mercy" value="1" />
      <Trait id="Valor" value="0" />
      <Trait id="Honor" value="1" />
      <Trait id="Generosity" value="1" />
      <Trait id="Calculating" value="2" />
      <Trait id="Egalitarian" value="0" />
      <Trait id="Oligarchic" value="0" />
      <Trait id="Authoritarian" value="0" />
    </Traits>
    <Equipments>
      <EquipmentSet id="hun_lord" />
      <EquipmentSet id="hun_lord"
                    civilian="true" />
    </Equipments>
  </NPCCharacter>

  <NPCCharacter id="lord_hungary_3e"
    name="{=lord_hungary_3e.name}Kecele"
    voice="softspoken"
    age="26"
    is_female="false"
    is_hero="true"
    culture="Culture.hungary"
    occupation="Lord"
    default_group="Cavalry">
    <face>
      <!-- Face key needs redoing, repurposed from female-->
      <BodyProperties version="4" age="22.13" weight="0.2755" build="0.2986"  key="0018A40C402C1006256854BAA29C387587367874B59A99B7A79A9B78D51965860054460305758995000000000000000000000000000000000000000028B42042"  />
    </face>
	  <skills>
      <skill id="Engineering" value="75" />
      <skill id="Medicine" value="50" />
      <skill id="Leadership" value="125" />
      <skill id="Steward" value="100" />
      <skill id="Trade" value="0" />
      <skill id="Charm" value="75" />
      <skill id="Roguery" value="175" />
      <skill id="Scouting" value="125" />
      <skill id="Tactics" value="125" />
      <skill id="Athletics" value="100" />
      <skill id="Riding" value="150" />
      <skill id="Throwing" value="75" />
      <skill id="Crossbow" value="75" />
      <skill id="Bow" value="75" />
      <skill id="Polearm" value="125" />
      <skill id="TwoHanded" value="75" />
      <skill id="OneHanded" value="125" />
    </skills>
    <Traits>
      <Trait id="Mercy" value="-1" />
      <Trait id="Valor" value="-2" />
      <Trait id="Honor" value="-2" />
      <Trait id="Generosity" value="0" />
      <Trait id="Calculating" value="1" />
      <Trait id="Egalitarian" value="0" />
      <Trait id="Oligarchic" value="0" />
      <Trait id="Authoritarian" value="0" />
    </Traits>
    <Equipments>
      <EquipmentSet id="hun_lord" />
      <EquipmentSet id="hun_lord"
                    civilian="true" />
    </Equipments>
  </NPCCharacter>

  <NPCCharacter id="lord_hungary_3f"
    name="{=lord_hungary_3f.name}Tivadar"
    voice="softspoken"
    age="25"
    is_female="false"
    is_hero="true"
    culture="Culture.hungary"
    occupation="Lord"
    default_group="Cavalry">
    <face>
      <!-- Face key needs redoing, repurposed from female-->
      <BodyProperties version="4" age="22.13" weight="0.6343" build="0.1752"  key="00186009802C338D279654B7A299387787367874959A99A7A7BA9379741665860083A60308658795000000000000000000000000000000000000000029041042"  />
    </face>
	  <skills>
      <skill id="Engineering" value="50" />
      <skill id="Medicine" value="50" />
      <skill id="Leadership" value="75" />
      <skill id="Steward" value="175" />
      <skill id="Trade" value="150" />
      <skill id="Charm" value="125" />
      <skill id="Roguery" value="125" />
      <skill id="Scouting" value="125" />
      <skill id="Tactics" value="125" />
      <skill id="Athletics" value="100" />
      <skill id="Riding" value="150" />
      <skill id="Throwing" value="25" />
      <skill id="Crossbow" value="75" />
      <skill id="Bow" value="75" />
      <skill id="Polearm" value="100" />
      <skill id="TwoHanded" value="50" />
      <skill id="OneHanded" value="100" />
    </skills>
    <Traits>
      <Trait id="Mercy" value="0" />
      <Trait id="Valor" value="-1" />
      <Trait id="Honor" value="-1" />
      <Trait id="Generosity" value="0" />
      <Trait id="Calculating" value="1" />
      <Trait id="Egalitarian" value="0" />
      <Trait id="Oligarchic" value="2" />
      <Trait id="Authoritarian" value="0" />
    </Traits>
    <Equipments>
      <EquipmentSet id="hun_lord" />
      <EquipmentSet id="hun_lord"
                    civilian="true" />
    </Equipments>
  </NPCCharacter>

  <NPCCharacter id="lord_hungary_3g"
    name="{=lord_hungary_3g.name}Cheme"
    voice="softspoken"
    age="22"
    is_female="false"
    is_hero="true"
    culture="Culture.hungary"
    occupation="Lord"
    default_group="Cavalry">
    <face>
      <!-- Face key needs redoing, repurposed from female-->
      <BodyProperties version="4" age="22.13" weight="0.615" build="0.6806"  key="0018400C4E2C13C1286854BA7499387785387874B5CC99A8A79A98A875196576008A960308A55965000000000000000000000000000000000000000028FC2042"  />
    </face>
	  <skills>
      <skill id="Engineering" value="75" />
      <skill id="Medicine" value="50" />
      <skill id="Leadership" value="125" />
      <skill id="Steward" value="75" />
      <skill id="Trade" value="25" />
      <skill id="Charm" value="100" />
      <skill id="Roguery" value="75" />
      <skill id="Scouting" value="75" />
      <skill id="Tactics" value="100" />
      <skill id="Athletics" value="100" />
      <skill id="Riding" value="125" />
      <skill id="Throwing" value="25" />
      <skill id="Crossbow" value="50" />
      <skill id="Bow" value="50" />
      <skill id="Polearm" value="150" />
      <skill id="TwoHanded" value="25" />
      <skill id="OneHanded" value="100" />
    </skills>
    <Traits>
      <Trait id="Mercy" value="-1" />
      <Trait id="Valor" value="1" />
      <Trait id="Honor" value="0" />
      <Trait id="Generosity" value="2" />
      <Trait id="Calculating" value="0" />
      <Trait id="Egalitarian" value="1" />
      <Trait id="Oligarchic" value="0" />
      <Trait id="Authoritarian" value="0" />
    </Traits>
    <Equipments>
      <EquipmentSet id="hun_lord" />
      <EquipmentSet id="hun_lord"
                    civilian="true" />
    </Equipments>
  </NPCCharacter>
  
  <NPCCharacter id="lord_hungary_4a"
                name="{=Dujam}Dujam"
                voice="softspoken"
                age="32"
                is_female="false"
                is_hero="true"
                culture="Culture.hungary"
                occupation="Lord"
                default_group="Cavalry">
    <face>
      <!-- Face key needs redoing, repurposed from female-->
 <BodyProperties version="4" age="22.21" weight="0.7595" build="0.4433"  key="00005C0E501407DB9AA84627A4A2963C8C79D73DC267EA3879C9AB58468692B50097B60309B46B5B0000000000000000000000000000000000000000473C6142"  />
    </face>
	<skills>
	<skill id="Leadership" value="86" />
<skill id="Scouting" value="175" />
<skill id="Tactics" value="188" />
<skill id="Athletics" value="68" />
<skill id="Riding" value="88" />
<skill id="Throwing" value="122" />
<skill id="Crossbow" value="26" />
<skill id="Bow" value="32" />
<skill id="Polearm" value="5" />
<skill id="TwoHanded" value="172" />
<skill id="OneHanded" value="193" />
</skills>
    <Traits>
<Trait id="Mercy" value="1" />
<Trait id="Valor" value="-2" />
<Trait id="Honor" value="2" />
<Trait id="Generosity" value="0" />
<Trait id="Calculating" value="0" />
<Trait id="Egalitarian" value="-1" />
<Trait id="Oligarchic" value="2" />
<Trait id="Authoritarian" value="1" />
    </Traits>
    <Equipments>
      <EquipmentSet id="hun_lord" />
      <EquipmentSet id="hun_lord"
                    civilian="true" />
    </Equipments>
  </NPCCharacter>
  
  <NPCCharacter id="lord_hungary_4b"
                name="{=Dalibora}Dalibora"
                default_group="Cavalry"
                age="29"
                voice="ironic"
                is_female="true"
                is_hero="true"
                culture="Culture.hungary"
                occupation="Lord"
                face_mesh_cache="true">
    <face>
  <BodyProperties version="4" age="22.21" weight="0.7595" build="0.4433"  key="00005C0E401410069AA84627A4A2963C8C79D73DC267EA3879C9AB58468692B50097B60309B46B5B0000000000000000000000000000000000000000473C40C3"  />
    </face>
    <skills>
	<skill id="Engineering" value="74" />
<skill id="Medicine" value="177" />
<skill id="Leadership" value="43" />
<skill id="Steward" value="95" />
<skill id="Trade" value="91" />
<skill id="Charm" value="123" />
<skill id="Roguery" value="115" />
<skill id="Scouting" value="49" />
<skill id="Crafting" value="84" />
	</skills>
    <Traits>
<Trait id="Mercy" value="0" />
<Trait id="Valor" value="2" />
<Trait id="Honor" value="0" />
<Trait id="Generosity" value="-2" />
<Trait id="Calculating" value="2" />
<Trait id="Egalitarian" value="-1" />
<Trait id="Oligarchic" value="1" />
<Trait id="Authoritarian" value="0" />
    </Traits>
    <Equipments>
      <EquipmentSet id="hun_lady" />
      <EquipmentSet id="hun_lady"
                    civilian="true" />
    </Equipments>
  </NPCCharacter>
  
  <NPCCharacter id="lord_hungary_5a"
                name="{=Gug}Gug"
                voice="softspoken"
                age="45"
                is_female="false"
                is_hero="true"
                culture="Culture.hungary"
                occupation="Lord"
                default_group="Cavalry">
    <face>
      <!-- Face key needs redoing, repurposed from female-->
  <BodyProperties version="4" age="22.21" weight="0.1269" build="0.4433"  key="0008D00D00CC149C76A2AA648AA5AD778926752688CC4BBB77166C966B96AC83009726030996983B000000000000000000000000000000000000000047345042"  />
    </face>
	<skills>
	<skill id="Leadership" value="106" />
<skill id="Scouting" value="53" />
<skill id="Tactics" value="42" />
<skill id="Athletics" value="150" />
<skill id="Riding" value="146" />
<skill id="Throwing" value="196" />
<skill id="Crossbow" value="37" />
<skill id="Bow" value="180" />
<skill id="Polearm" value="65" />
<skill id="TwoHanded" value="150" />
<skill id="OneHanded" value="94" />
</skills>
    <Traits>
<Trait id="Mercy" value="-2" />
<Trait id="Valor" value="-1" />
<Trait id="Honor" value="-1" />
<Trait id="Generosity" value="-2" />
<Trait id="Calculating" value="0" />
<Trait id="Egalitarian" value="-2" />
<Trait id="Oligarchic" value="-1" />
<Trait id="Authoritarian" value="-2" />
    </Traits>
    <Equipments>
      <EquipmentSet id="hun_lord" />
      <EquipmentSet id="hun_lord"
                    civilian="true" />
    </Equipments>
  </NPCCharacter>
  
  <NPCCharacter id="lord_hungary_5b"
                name="{=Emilja}Emilja"
                default_group="Cavalry"
                age="41"
                voice="ironic"
                is_female="true"
                is_hero="true"
                culture="Culture.hungary"
                occupation="Lord"
                face_mesh_cache="true">
    <face>
  <BodyProperties version="4" age="22.21" weight="0.6861" build="0.4433"  key="0010500A4088000632A254928375C7BB827875D1A986AB887A199758BEBA6A860067A603067ADC8B00000000000000000000000000000000000000006CCC40C3"  />
    </face>
    <skills>
	<skill id="Engineering" value="124" />
<skill id="Medicine" value="28" />
<skill id="Leadership" value="137" />
<skill id="Steward" value="63" />
<skill id="Trade" value="40" />
<skill id="Charm" value="6" />
<skill id="Roguery" value="178" />
<skill id="Scouting" value="22" />
<skill id="Crafting" value="13" />
	</skills>
    <Traits>
<Trait id="Mercy" value="0" />
<Trait id="Valor" value="-2" />
<Trait id="Honor" value="1" />
<Trait id="Generosity" value="-2" />
<Trait id="Calculating" value="-2" />
<Trait id="Egalitarian" value="1" />
<Trait id="Oligarchic" value="-2" />
<Trait id="Authoritarian" value="1" />
    </Traits>
    <Equipments>
      <EquipmentSet id="hun_lady" />
      <EquipmentSet id="hun_lady"
                    civilian="true" />
    </Equipments>
  </NPCCharacter>
  
  <NPCCharacter id="lord_hungary_6a"
                name="{=Julius}Julius"
                voice="softspoken"
                age="33"
                is_female="false"
                is_hero="true"
                culture="Culture.hungary"
                occupation="Lord"
                default_group="Cavalry">
    <face>
      <!-- Face key needs redoing, repurposed from female-->
  <BodyProperties version="4" age="22.21" weight="0.3913" build="0.4433"  key="00106006C02C36011CAC047CD6AA9BD685587B91C483A98975BB4567D7764AB3008766030845294700000000000000000000000000000000000000000D047002"  />
    </face>
	<skills>
	<skill id="Leadership" value="156" />
<skill id="Scouting" value="52" />
<skill id="Tactics" value="195" />
<skill id="Athletics" value="80" />
<skill id="Riding" value="15" />
<skill id="Throwing" value="194" />
<skill id="Crossbow" value="170" />
<skill id="Bow" value="117" />
<skill id="Polearm" value="41" />
<skill id="TwoHanded" value="31" />
<skill id="OneHanded" value="47" />
</skills>
    <Traits>
<Trait id="Mercy" value="2" />
<Trait id="Valor" value="1" />
<Trait id="Honor" value="-2" />
<Trait id="Generosity" value="-2" />
<Trait id="Calculating" value="-2" />
<Trait id="Egalitarian" value="-1" />
<Trait id="Oligarchic" value="1" />
<Trait id="Authoritarian" value="-2" />
    </Traits>
    <Equipments>
      <EquipmentSet id="hun_lord" />
      <EquipmentSet id="hun_lord"
                    civilian="true" />
    </Equipments>
  </NPCCharacter>
  
  <NPCCharacter id="lord_hungary_6b"
                name="{=Tereza}Tereza"
                default_group="Cavalry"
                age="28"
                voice="ironic"
                is_female="true"
                is_hero="true"
                culture="Culture.hungary"
                occupation="Lord"
                face_mesh_cache="true">
    <face>
   <BodyProperties version="4" age="22.21" weight="0.3913" build="0.4433"  key="00106006C02C00061CAC047CD6AA9BD685587B91C483A98975BB4567D7764AB3008766030845294700000000000000000000000000000000000000000D0440C3"  />
    </face>
    <skills>
	<skill id="Engineering" value="128" />
<skill id="Medicine" value="145" />
<skill id="Leadership" value="93" />
<skill id="Steward" value="128" />
<skill id="Trade" value="0" />
<skill id="Charm" value="107" />
<skill id="Roguery" value="99" />
<skill id="Scouting" value="9" />
<skill id="Crafting" value="9" />
	</skills>
    <Traits>
<Trait id="Mercy" value="-2" />
<Trait id="Valor" value="-2" />
<Trait id="Honor" value="-1" />
<Trait id="Generosity" value="-1" />
<Trait id="Calculating" value="1" />
<Trait id="Egalitarian" value="2" />
<Trait id="Oligarchic" value="0" />
<Trait id="Authoritarian" value="-2" />
    </Traits>
    <Equipments>
      <EquipmentSet id="hun_lady" />
      <EquipmentSet id="hun_lady"
                    civilian="true" />
    </Equipments>
  </NPCCharacter>
  
  <NPCCharacter id="lord_hungary_7a"
                name="{=Merkúr}Merkúr"
                voice="softspoken"
                age="35"
                is_female="false"
                is_hero="true"
                culture="Culture.hungary"
                occupation="Lord"
                default_group="Cavalry">
    <face>
      <!-- Face key needs redoing, repurposed from female-->
<BodyProperties version="4" age="22.04" weight="0.5" build="0.6697"  key="0013300FC0003182B7366617D7285DBA8EB9B96D8CC688635577DAAD5856A7A900CA76030C39502600000000000000000000000000000000000000001F8C20C2"  />
    </face>
	<skills>
<skill id="Leadership" value="1" />
<skill id="Scouting" value="27" />
<skill id="Tactics" value="198" />
<skill id="Athletics" value="166" />
<skill id="Riding" value="11" />
<skill id="Throwing" value="146" />
<skill id="Crossbow" value="146" />
<skill id="Bow" value="175" />
<skill id="Polearm" value="43" />
<skill id="TwoHanded" value="75" />
<skill id="OneHanded" value="185" />
</skills>
    <Traits>
<Trait id="Mercy" value="0" />
<Trait id="Valor" value="2" />
<Trait id="Honor" value="-2" />
<Trait id="Generosity" value="-2" />
<Trait id="Calculating" value="2" />
<Trait id="Egalitarian" value="-2" />
<Trait id="Oligarchic" value="0" />
<Trait id="Authoritarian" value="0" />
    </Traits>
    <Equipments>
      <EquipmentSet id="hun_lord" />
      <EquipmentSet id="hun_lord"
                    civilian="true" />
    </Equipments>
  </NPCCharacter>
  
  <NPCCharacter id="lord_hungary_7b"
                name="{=Zoé}Zoé"
                default_group="Cavalry"
                age="30"
                voice="ironic"
                is_female="true"
                is_hero="true"
                culture="Culture.hungary"
                occupation="Lord"
                face_mesh_cache="true">
    <face>
<BodyProperties version="4" age="22.04" weight="0.5" build="0.6697"  key="0013E00FC0003002B7366617D7285DBA8EB9B96D8CC688635577DAAD5856A7A900CA76030C39502600000000000000000000000000000000000000001F8C20C3"  />
    </face>
    <skills>
<skill id="Engineering" value="21" />
<skill id="Medicine" value="10" />
<skill id="Leadership" value="26" />
<skill id="Steward" value="50" />
<skill id="Trade" value="35" />
<skill id="Charm" value="74" />
<skill id="Roguery" value="31" />
<skill id="Scouting" value="34" />
<skill id="Crafting" value="74" />
	</skills>
    <Traits>
<Trait id="Mercy" value="0" />
<Trait id="Valor" value="2" />
<Trait id="Honor" value="-2" />
<Trait id="Generosity" value="-2" />
<Trait id="Calculating" value="2" />
<Trait id="Egalitarian" value="-2" />
<Trait id="Oligarchic" value="0" />
<Trait id="Authoritarian" value="0" />
    </Traits>
    <Equipments>
      <EquipmentSet id="hun_lady" />
      <EquipmentSet id="hun_lady"
                    civilian="true" />
    </Equipments>
  </NPCCharacter>


  <NPCCharacter id="lord_hungary_8a"
                name="{=lord_latgalian_2a.name}Saulnesis*"
                voice="softspoken"
                age="37"
                is_female="false"
                is_hero="true"
                culture="Culture.hungary"
                occupation="Lord"
                default_group="Cavalry">
    <face>
    <!-- Face key needs redoing, repurposed from female-->
    <BodyProperties version="4" age="22" weight="0.3218" build="0.3995"  key="000D8C0980882594A5DCA5C66719BC9CD58C88847BAB71438875A5AC3C9A775800B656030B5342A500000000000000000000000000000000000000003D6C2042"  />
        </face>
    <skills>
        <skill id="Engineering" value="150" />
        <skill id="Medicine" value="100" />
        <skill id="Leadership" value="175" />
        <skill id="Steward" value="150" />
        <skill id="Trade" value="50" />
        <skill id="Charm" value="50" />
        <skill id="Roguery" value="125" />
        <skill id="Scouting" value="175" />
        <skill id="Tactics" value="175" />
        <skill id="Athletics" value="225" />
        <skill id="Riding" value="100" />
        <skill id="Throwing" value="125" />
        <skill id="Bow" value="100" />
        <skill id="Polearm" value="225" />
        <skill id="TwoHanded" value="125" />
        <skill id="OneHanded" value="200" />
    </skills>
    <Traits>
        <Trait id="Mercy" value="1" />
        <Trait id="Valor" value="1" />
        <Trait id="Honor" value="0" />
        <Trait id="Generosity" value="1" />
        <Trait id="Calculating" value="0" />
        <Trait id="Egalitarian" value="0" />
        <Trait id="Oligarchic" value="0" />
        <Trait id="Authoritarian" value="0" />
    </Traits>
    <Equipments>
        <EquipmentSet id="hun_lord" />
        <EquipmentSet id="hun_lord"
                        civilian="true" />
    </Equipments>
    </NPCCharacter>

  <NPCCharacter id="lord_hungary_9a"
                name="{=lord_latgalian_2a.name}Saulnesis*"
                voice="softspoken"
                age="37"
                is_female="false"
                is_hero="true"
                culture="Culture.hungary"
                occupation="Lord"
                default_group="Cavalry">
    <face>
    <!-- Face key needs redoing, repurposed from female-->
    <BodyProperties version="4" age="22" weight="0.3218" build="0.3995"  key="000D8C0980882594A5DCA5C66719BC9CD58C88847BAB71438875A5AC3C9A775800B656030B5342A500000000000000000000000000000000000000003D6C2042"  />
        </face>
    <skills>
        <skill id="Engineering" value="150" />
        <skill id="Medicine" value="100" />
        <skill id="Leadership" value="175" />
        <skill id="Steward" value="150" />
        <skill id="Trade" value="50" />
        <skill id="Charm" value="50" />
        <skill id="Roguery" value="125" />
        <skill id="Scouting" value="175" />
        <skill id="Tactics" value="175" />
        <skill id="Athletics" value="225" />
        <skill id="Riding" value="100" />
        <skill id="Throwing" value="125" />
        <skill id="Bow" value="100" />
        <skill id="Polearm" value="225" />
        <skill id="TwoHanded" value="125" />
        <skill id="OneHanded" value="200" />
    </skills>
    <Traits>
        <Trait id="Mercy" value="1" />
        <Trait id="Valor" value="1" />
        <Trait id="Honor" value="0" />
        <Trait id="Generosity" value="1" />
        <Trait id="Calculating" value="0" />
        <Trait id="Egalitarian" value="0" />
        <Trait id="Oligarchic" value="0" />
        <Trait id="Authoritarian" value="0" />
    </Traits>
    <Equipments>
        <EquipmentSet id="hun_lord" />
        <EquipmentSet id="hun_lord"
                        civilian="true" />
    </Equipments>
    </NPCCharacter>

  <NPCCharacter id="lord_hungary_10a"
                name="{=lord_latgalian_2a.name}Saulnesis*"
                voice="softspoken"
                age="37"
                is_female="false"
                is_hero="true"
                culture="Culture.hungary"
                occupation="Lord"
                default_group="Cavalry">
    <face>
    <!-- Face key needs redoing, repurposed from female-->
    <BodyProperties version="4" age="22" weight="0.3218" build="0.3995"  key="000D8C0980882594A5DCA5C66719BC9CD58C88847BAB71438875A5AC3C9A775800B656030B5342A500000000000000000000000000000000000000003D6C2042"  />
        </face>
    <skills>
        <skill id="Engineering" value="150" />
        <skill id="Medicine" value="100" />
        <skill id="Leadership" value="175" />
        <skill id="Steward" value="150" />
        <skill id="Trade" value="50" />
        <skill id="Charm" value="50" />
        <skill id="Roguery" value="125" />
        <skill id="Scouting" value="175" />
        <skill id="Tactics" value="175" />
        <skill id="Athletics" value="225" />
        <skill id="Riding" value="100" />
        <skill id="Throwing" value="125" />
        <skill id="Bow" value="100" />
        <skill id="Polearm" value="225" />
        <skill id="TwoHanded" value="125" />
        <skill id="OneHanded" value="200" />
    </skills>
    <Traits>
        <Trait id="Mercy" value="1" />
        <Trait id="Valor" value="1" />
        <Trait id="Honor" value="0" />
        <Trait id="Generosity" value="1" />
        <Trait id="Calculating" value="0" />
        <Trait id="Egalitarian" value="0" />
        <Trait id="Oligarchic" value="0" />
        <Trait id="Authoritarian" value="0" />
    </Traits>
    <Equipments>
        <EquipmentSet id="hun_lord" />
        <EquipmentSet id="hun_lord"
                        civilian="true" />
    </Equipments>
    </NPCCharacter>
  
  <NPCCharacter id="lord_hungary_11a"
                name="{=lord_latgalian_2a.name}Saulnesis*"
                voice="softspoken"
                age="37"
                is_female="false"
                is_hero="true"
                culture="Culture.hungary"
                occupation="Lord"
                default_group="Cavalry">
    <face>
    <!-- Face key needs redoing, repurposed from female-->
    <BodyProperties version="4" age="22" weight="0.3218" build="0.3995"  key="000D8C0980882594A5DCA5C66719BC9CD58C88847BAB71438875A5AC3C9A775800B656030B5342A500000000000000000000000000000000000000003D6C2042"  />
        </face>
    <skills>
        <skill id="Engineering" value="150" />
        <skill id="Medicine" value="100" />
        <skill id="Leadership" value="175" />
        <skill id="Steward" value="150" />
        <skill id="Trade" value="50" />
        <skill id="Charm" value="50" />
        <skill id="Roguery" value="125" />
        <skill id="Scouting" value="175" />
        <skill id="Tactics" value="175" />
        <skill id="Athletics" value="225" />
        <skill id="Riding" value="100" />
        <skill id="Throwing" value="125" />
        <skill id="Bow" value="100" />
        <skill id="Polearm" value="225" />
        <skill id="TwoHanded" value="125" />
        <skill id="OneHanded" value="200" />
    </skills>
    <Traits>
        <Trait id="Mercy" value="1" />
        <Trait id="Valor" value="1" />
        <Trait id="Honor" value="0" />
        <Trait id="Generosity" value="1" />
        <Trait id="Calculating" value="0" />
        <Trait id="Egalitarian" value="0" />
        <Trait id="Oligarchic" value="0" />
        <Trait id="Authoritarian" value="0" />
    </Traits>
    <Equipments>
        <EquipmentSet id="hun_lord" />
        <EquipmentSet id="hun_lord"
                        civilian="true" />
    </Equipments>
    </NPCCharacter>

    <NPCCharacter id="lord_hungary_12a"
                name="{=lord_latgalian_2a.name}Saulnesis*"
                voice="softspoken"
                age="37"
                is_female="false"
                is_hero="true"
                culture="Culture.hungary"
                occupation="Lord"
                default_group="Cavalry">
    <face>
    <!-- Face key needs redoing, repurposed from female-->
    <BodyProperties version="4" age="22" weight="0.3218" build="0.3995"  key="000D8C0980882594A5DCA5C66719BC9CD58C88847BAB71438875A5AC3C9A775800B656030B5342A500000000000000000000000000000000000000003D6C2042"  />
        </face>
    <skills>
        <skill id="Engineering" value="150" />
        <skill id="Medicine" value="100" />
        <skill id="Leadership" value="175" />
        <skill id="Steward" value="150" />
        <skill id="Trade" value="50" />
        <skill id="Charm" value="50" />
        <skill id="Roguery" value="125" />
        <skill id="Scouting" value="175" />
        <skill id="Tactics" value="175" />
        <skill id="Athletics" value="225" />
        <skill id="Riding" value="100" />
        <skill id="Throwing" value="125" />
        <skill id="Bow" value="100" />
        <skill id="Polearm" value="225" />
        <skill id="TwoHanded" value="125" />
        <skill id="OneHanded" value="200" />
    </skills>
    <Traits>
        <Trait id="Mercy" value="1" />
        <Trait id="Valor" value="1" />
        <Trait id="Honor" value="0" />
        <Trait id="Generosity" value="1" />
        <Trait id="Calculating" value="0" />
        <Trait id="Egalitarian" value="0" />
        <Trait id="Oligarchic" value="0" />
        <Trait id="Authoritarian" value="0" />
    </Traits>
    <Equipments>
        <EquipmentSet id="hun_lord" />
        <EquipmentSet id="hun_lord"
                        civilian="true" />
    </Equipments>
    </NPCCharacter>

</NPCCharacters>